{
    "state": {
        "grid": {
            "row_size": 6,
            "col_size": 6,
            "cells": {}
        },
        "horizontalcars": [
            {
                "name": "red-car",
                "x": 0,
                "y": 2
            },
            {
                "name": "blue-car",
                "x": 2,
                "y": 0
            },
            {
                "name": "purple-car",
                "x": 2,
                "y": 1
            }
        ],
        "verticalcars": [
            {
                "name": "green-car",
                "x": 0,
                "y": 0
            },
            {
                "name": "orange-car",
                "x": 1,
                "y": 0
            },
            {
                "name": "white-car",
                "x": 4,
                "y": 3
            },
            {
                "name": "pink-car",
                "x": 4,
                "y": 0
            },
            {
                "name": "green-over-car",
                "x": 2,
                "y": 2
            },
            {
                "name": "yellow-over-car",
                "x": 2,
                "y": 4
            }
        ],
        "horizontaltrucks": [],
        "verticaltrucks": [
            {
                "name": "yellow-truck",
                "x": 3,
                "y": 2
            }
        ]
    }
}